<root>

TRY CHANGING GRAVITY ANGLE TO GENTLY START SWIGGING PROCESS...


<body type="plane" name="plane1" p="0 -10.0 0" n="0 1 0"></body>
<body type="box" name="S0B0" dim="8.0  1.0 8.0">
    <x> 0.0  0.4999 0.0 </x>
    <R> 0 -1 0 0.24908244283927838</R>
   <col> 0.686274528503418  0.7490196228027344 0.6000000238418579 </col>
</body>
<body type="box" name="S0B1" dim="8.0  1.0 8.0">
    <x> 0.0  1.4997 0.0 </x>
    <R> 0 -1 0 -0.07655942361564105</R>
   <col> 0.6352941393852234  0.6000000238418579 0.7490196228027344 </col>
</body>
<body type="box" name="S0B2" dim="8.0  1.0 8.0">
    <x> 0.0  2.4995000000000003 0.0 </x>
    <R> 0 -1 0 0.08521794784555425</R>
   <col> 0.7490196228027344  0.6000000238418579 0.6431372761726379 </col>
</body>
<body type="box" name="S0B3" dim="8.0  1.0 8.0">
    <x> 0.0  3.4993000000000007 0.0 </x>
    <R> 0 -1 0 -0.12186077509068893</R>
   <col> 0.6980392336845398  0.7490196228027344 0.6000000238418579 </col>
</body>
<body type="box" name="S0B4" dim="8.0  1.0 8.0">
    <x> 0.0  4.499100000000001 0.0 </x>
    <R> 0 -1 0 -0.051455207293139904</R>
   <col> 0.7490196228027344  0.6000000238418579 0.729411780834198 </col>
</body>
<body type="box" name="S0B5" dim="8.0  1.0 8.0">
    <x> 0.0  5.498900000000002 0.0 </x>
    <R> 0 -1 0 -0.10865582987025413</R>
   <col> 0.7490196228027344  0.6784313917160034 0.6000000238418579 </col>
</body>
<body type="box" name="S0B6" dim="8.0  1.0 8.0">
    <x> 0.0  6.498700000000002 0.0 </x>
    <R> 0 -1 0 -0.010403821922192247</R>
   <col> 0.6705882549285889  0.7490196228027344 0.6000000238418579 </col>
</body>
<body type="box" name="S0B7" dim="8.0  1.0 8.0">
    <x> 0.0  7.498500000000003 0.0 </x>
    <R> 0 -1 0 -0.17063584546774474</R>
   <col> 0.7490196228027344  0.6000000238418579 0.7058823704719543 </col>
</body>
<body type="box" name="S0B8" dim="8.0  1.0 8.0">
    <x> 0.0  8.498300000000002 0.0 </x>
    <R> 0 -1 0 0.07838137274141882</R>
   <col> 0.7490196228027344  0.6000000238418579 0.7333333492279053 </col>
</body>
<body type="box" name="S0B9" dim="8.0  1.0 8.0">
    <x> 0.0  9.498100000000003 0.0 </x>
    <R> 0 -1 0 -0.23376308189692518</R>
   <col> 0.6549019813537598  0.6000000238418579 0.7490196228027344 </col>
</body>
<body type="box" name="S0B10" dim="8.0  1.0 8.0">
    <x> 0.0  10.497900000000003 0.0 </x>
    <R> 0 -1 0 -0.08498720521306458</R>
   <col> 0.7490196228027344  0.6000000238418579 0.6313725709915161 </col>
</body>
<body type="box" name="S0B11" dim="8.0  1.0 8.0">
    <x> 0.0  11.497700000000004 0.0 </x>
    <R> 0 -1 0 0.09478759182098617</R>
   <col> 0.7490196228027344  0.6000000238418579 0.7411764860153198 </col>
</body>
<body type="box" name="S0B12" dim="8.0  1.0 8.0">
    <x> 0.0  12.497500000000004 0.0 </x>
    <R> 0 -1 0 0.15373532879495</R>
   <col> 0.6000000238418579  0.6039215922355652 0.7490196228027344 </col>
</body>
<body type="box" name="S0B13" dim="8.0  1.0 8.0">
    <x> 0.0  13.497300000000005 0.0 </x>
    <R> 0 -1 0 -0.026211598159252558</R>
   <col> 0.6000000238418579  0.7490196228027344 0.6039215922355652 </col>
</body>
<body type="box" name="S0B14" dim="8.0  1.0 8.0">
    <x> 0.0  14.497100000000005 0.0 </x>
    <R> 0 -1 0 0.059690516294486795</R>
   <col> 0.7490196228027344  0.6000000238418579 0.6470588445663452 </col>
</body>
<body type="box" name="platform0" dim="20.0 1 20.0">
    <x> 0.0  -0.5 0.0 </x>
    <spring pB="-10.0  0.5 -10.0" pW="0.0  50.0 0.0" k="500.0" d="200.0"/>
    <spring pB="-10.0  0.5 10.0" pW="0.0  50.0 0.0" k="500.0" d="200.0"/>
    <spring pB="10.0  0.5 -10.0" pW="0.0  50.0 0.0" k="500.0" d="200.0"/>
    <spring pB="10.0  0.5 10.0" pW="0.0  50.0 0.0" k="500.0" d="200.0"/>
</body>
</root>
